currex/__init__.py
currex/config.py
currex/currency.py
currex/exchange.py
currex/factory.py
currex-0.2.0.dist-info/METADATA
currex-0.2.0.dist-info/WHEEL
currex-0.2.0.dist-info/licenses/LICENSE
currex-0.2.0.dist-info/RECORD
